jakt/__init__.py
jakt/__main__.py
jakt/cli.py
jakt/exceptions.py
jakt/report.py
jakt/timeslot.py
jakt-0.0.7.dist-info/LICENSE
jakt-0.0.7.dist-info/METADATA
jakt-0.0.7.dist-info/WHEEL
jakt-0.0.7.dist-info/entry_points.txt
jakt-0.0.7.dist-info/top_level.txt
jakt-0.0.7.dist-info/RECORD
