Metadata-Version: 2.1
Name: jakt
Version: 0.0.7
Summary: Just another (k)ommandline timetracker
Author-email: kwillno <kristian@kwill.no>
Project-URL: Homepage, https://github.com/kwillno/jakt
Project-URL: Bug Tracker, https://github.com/kwillno/jakt/issues
Classifier: Programming Language :: Python :: 3
Classifier: License :: OSI Approved :: MIT License
Classifier: Operating System :: POSIX
Requires-Python: >=3.7
License-File: LICENSE
Requires-Dist: click
Requires-Dist: platformdirs
